pycturing/__init__.py
pycturing/bezier.py
pycturing/util.py
pycturing/asset/__init__.py
pycturing/asset/font.py
pycturing/text/__init__.py
pycturing/text/util.py
pycturing-0.0.3.dist-info/METADATA
pycturing-0.0.3.dist-info/WHEEL
pycturing-0.0.3.dist-info/license
pycturing-0.0.3.dist-info/top_level.txt
pycturing-0.0.3.dist-info/RECORD
